processors/__init__.py
processors/text_processor.py
processors-0.0.12.dist-info/LICENSE
processors-0.0.12.dist-info/METADATA
processors-0.0.12.dist-info/WHEEL
processors-0.0.12.dist-info/top_level.txt
processors-0.0.12.dist-info/RECORD
