Metadata-Version: 2.1
Name: processors
Version: 0.0.12
Summary: Allows easy clean up of text
Home-page: https://github.com/tools4eu/processors
Author: tools4eu
Author-email: openeuro@proton.me
Project-URL: Bug Tracker, https://github.com/tools4eu/processors/issues
Classifier: Programming Language :: Python :: 3
Classifier: License :: OSI Approved :: MIT License
Classifier: Operating System :: OS Independent
Requires-Python: >=3.6
License-File: LICENSE
Requires-Dist: demoji
